spike2py_reflex/__init__.py
spike2py_reflex/__main__.py
spike2py_reflex/process.py
spike2py_reflex/info/__init__.py
spike2py_reflex/info/channels.py
spike2py_reflex/info/info.py
spike2py_reflex/info/stim_params.py
spike2py_reflex/info/trials_sections.py
spike2py_reflex/info/windows.py
spike2py_reflex/outcomes/__init__.py
spike2py_reflex/outcomes/mean_outcomes.py
spike2py_reflex/outcomes/outcomes_of_avg_reflex.py
spike2py_reflex/outcomes/reflex_outcomes.py
spike2py_reflex/outcomes/summary.py
spike2py_reflex/outcomes/utils.py
spike2py_reflex/plot/__init__.py
spike2py_reflex/plot/double.py
spike2py_reflex/plot/outcomes.py
spike2py_reflex/plot/plots.py
spike2py_reflex/plot/reflexes.py
spike2py_reflex/plot/single.py
spike2py_reflex/plot/train.py
spike2py_reflex/reflexes/__init__.py
spike2py_reflex/reflexes/extract.py
spike2py_reflex/reflexes/utils.py
spike2py_reflex/utils/__init__.py
spike2py_reflex/utils/constants.py
spike2py_reflex/utils/stim_intensity.py
spike2py_reflex/utils/triggers.py
spike2py_reflex-0.0.18.dist-info/METADATA
spike2py_reflex-0.0.18.dist-info/WHEEL
spike2py_reflex-0.0.18.dist-info/top_level.txt
spike2py_reflex-0.0.18.dist-info/RECORD
