Metadata-Version: 2.2
Name: spike2py_reflex
Version: 0.0.18
Summary: "Extract reflexes from preprocessed data with spike2py."
Home-page: https://github.com/MartinHeroux/spike2py_reflex
Author: Martin Heroux
Author-email: "Martin Heroux" <heroux.martin@gmail.com>
License: GPLv3
Classifier: License :: OSI Approved :: GNU General Public License v3 (GPLv3)
Classifier: Programming Language :: Python :: 3
Classifier: Programming Language :: Python :: 3.9
Classifier: Programming Language :: Python :: 3.10
Classifier: Programming Language :: Python :: 3.11
Classifier: Intended Audience :: Science/Research
Requires-Python: >=3.10
Requires-Dist: spike2py_preprocess
Requires-Dist: rich
Requires-Dist: typer
